LICENSE
README.md
setup.py
pulumi_k0s/__init__.py
pulumi_k0s/_inputs.py
pulumi_k0s/_utilities.py
pulumi_k0s/cluster.py
pulumi_k0s/outputs.py
pulumi_k0s/provider.py
pulumi_k0s/pulumi-plugin.json
pulumi_k0s/py.typed
pulumi_k0s.egg-info/PKG-INFO
pulumi_k0s.egg-info/SOURCES.txt
pulumi_k0s.egg-info/dependency_links.txt
pulumi_k0s.egg-info/not-zip-safe
pulumi_k0s.egg-info/requires.txt
pulumi_k0s.egg-info/top_level.txt
pulumi_k0s/config/__init__.py
pulumi_k0s/config/vars.py