Metadata-Version: 2.1
Name: pulumi-k0s
Version: 0.3.0
Summary: A Pulumi package for creating and managing k0s clusters.
Home-page: https://github.com/ydkn/pulumi-k0s
License: Apache-2.0
Project-URL: Repository, https://github.com/ydkn/pulumi-k0s
Keywords: pulumi kubernetes k0s
Requires-Python: >=3.8
License-File: LICENSE
